Workbook

Sheet Revenue
A1: invoice_no | B1: job | C1: amount
A2: INV-719 | B2: Quarry Road Nursery | C2: 67428.56
A3: INV-724 | B3: Ellington Bakery | C3: 49817.44
A4: INV-707 | B4: Cedar Point Clinic | C4: 79090.67
A5: INV-713 | B5: Tamarack Taproom | C5: 34421.07
A6: INV-732 | B6: Northfield Auto Body | C6: 52579.88
A7: INV-729 | B7: Wren & Sparrow Bookshop | C7: 70111.65
A8: INV-705 | B8: Cedar Point Clinic | C8: 56317.69
A9: INV-702 | B9: Harborview Lofts | C9: 73710.25
A10: INV-727 | B10: Wren & Sparrow Bookshop | C10: 80291.33
A11: INV-716 | B11: Silverline HQ | C11: 66103.59
A12: INV-723 | B12: Ellington Bakery | C12: 61167.01
A13: INV-712 | B13: Tamarack Taproom | C13: 59051.5
... A26: INV-708 | B26: Cedar Point Clinic | C26: 81639.59

Sheet Costs
A1: cost_id | B1: job | C1: category | D1: amount
A2: C-5005 | B2: Harborview Lofts | C2: Labour | D2: 9164.28
A3: C-5015 | B3: Harborview Lofts | C3: Subcontractor | D3: 7567.52
A4: C-5132 | B4: Wren & Sparrow Bookshop | C4: Subcontractor | D4: 8412.77
A5: C-5119 | B5: Ellington Bakery | C5: Travel | D5: 2366.21
A6: C-5079 | B6: Silverline HQ | C6: Materials | D6: 2494.17
A7: C-5014 | B7: Harborview Lofts | C7: Materials | D7: 8144.03
A8: C-5050 | B8: Tamarack Taproom | C8: Subcontractor | D8: 3586.31
A9: C-5148 | B9: Northfield Auto Body | C9: Materials | D9: 4961.38
A10: C-5167 | B10: Umber Ceramics Studio | C10: Subcontractor | D10: 1396.47
A11: C-5180 | B11: Umber Ceramics Studio | C11: Materials | D11: 1705.04
A12: C-5169 | B12: Umber Ceramics Studio | C12: Labour | D12: 1998.44
A13: C-5078 | B13: Silverline HQ | C13: Subcontractor | D13: 2357.19
... A429: UB-232 | B429: Northfield Auto Body | C429: Unbilled time | D429: 1728

Sheet Report
A1: Job | B1: Code | C1: Revenue | D1: Cost | E1: Margin | F1: Margin % | G1: Flag
A2: Harborview Lofts | B2: P-2401 | C2: =SUMIF(Revenue!$B$2:$B$26,$A2,Revenue!$C$2:$C$26) | D2: =SUMIF(Costs!$B$2:$B$429,$A2,Costs!$D$2:$D$429) | E2: =C2-D2 | F2: =IF(C2=0,"n/a",ROUND(E2/C2,4)) | G2: =IF(E2<0,"NEGATIVE","")
A3: Cedar Point Clinic | B3: P-2402 | C3: =SUMIF(Revenue!$B$2:$B$26,$A3,Revenue!$C$2:$C$26) | D3: =SUMIF(Costs!$B$2:$B$429,$A3,Costs!$D$2:$D$429) | E3: =C3-D3 | F3: =IF(C3=0,"n/a",ROUND(E3/C3,4)) | G3: =IF(E3<0,"NEGATIVE","")
A4: Tamarack Taproom | B4: P-2403 | C4: =SUMIF(Revenue!$B$2:$B$26,$A4,Revenue!$C$2:$C$26) | D4: =SUMIF(Costs!$B$2:$B$429,$A4,Costs!$D$2:$D$429) | E4: =C4-D4 | F4: =IF(C4=0,"n/a",ROUND(E4/C4,4)) | G4: =IF(E4<0,"NEGATIVE","")
A5: Silverline HQ | B5: P-2404 | C5: =SUMIF(Revenue!$B$2:$B$26,$A5,Revenue!$C$2:$C$26) | D5: =SUMIF(Costs!$B$2:$B$429,$A5,Costs!$D$2:$D$429) | E5: =C5-D5 | F5: =IF(C5=0,"n/a",ROUND(E5/C5,4)) | G5: =IF(E5<0,"NEGATIVE","")
A6: Quarry Road Nursery | B6: P-2405 | C6: =SUMIF(Revenue!$B$2:$B$26,$A6,Revenue!$C$2:$C$26) | D6: =SUMIF(Costs!$B$2:$B$429,$A6,Costs!$D$2:$D$429) | E6: =C6-D6 | F6: =IF(C6=0,"n/a",ROUND(E6/C6,4)) | G6: =IF(E6<0,"NEGATIVE","")
A7: Ellington Bakery | B7: P-2406 | C7: =SUMIF(Revenue!$B$2:$B$26,$A7,Revenue!$C$2:$C$26) | D7: =SUMIF(Costs!$B$2:$B$429,$A7,Costs!$D$2:$D$429) | E7: =C7-D7 | F7: =IF(C7=0,"n/a",ROUND(E7/C7,4)) | G7: =IF(E7<0,"NEGATIVE","")
A8: Wren & Sparrow Bookshop | B8: P-2407 | C8: =SUMIF(Revenue!$B$2:$B$26,$A8,Revenue!$C$2:$C$26) | D8: =SUMIF(Costs!$B$2:$B$429,$A8,Costs!$D$2:$D$429) | E8: =C8-D8 | F8: =IF(C8=0,"n/a",ROUND(E8/C8,4)) | G8: =IF(E8<0,"NEGATIVE","")
A9: Northfield Auto Body | B9: P-2408 | C9: =SUMIF(Revenue!$B$2:$B$26,$A9,Revenue!$C$2:$C$26) | D9: =SUMIF(Costs!$B$2:$B$429,$A9,Costs!$D$2:$D$429) | E9: =C9-D9 | F9: =IF(C9=0,"n/a",ROUND(E9/C9,4)) | G9: =IF(E9<0,"NEGATIVE","")
A10: Umber Ceramics Studio | B10: P-2409 | C10: =SUMIF(Revenue!$B$2:$B$26,$A10,Revenue!$C$2:$C$26) | D10: =SUMIF(Costs!$B$2:$B$429,$A10,Costs!$D$2:$D$429) | E10: =C10-D10 | F10: =IF(C10=0,"n/a",ROUND(E10/C10,4)) | G10: =IF(E10<0,"NEGATIVE","")
A11: Total - all jobs | C11: =SUM(C2:C10) | D11: =SUM(D2:D10) | E11: =SUM(E2:E10) | F11: =IF(C11=0,"n/a",ROUND(E11/C11,4))
A13: Revenue is invoiced work only (drafts and write-offs excluded). Cost includes unbilled hours at cost rate and is net of vendor credits.
