Workbook

Sheet Schedule
A1: Vendor | B1: Item | C1: Coverage start | D1: Last covered day | E1: Amount paid | F1: Balance 2026-01-01 | G1: Paid in 2026 | H1: Refund received | I1: 2026-01 | J1: 2026-02 | K1: 2026-03 | L1: 2026-04 | M1: 2026-05 | N1: 2026-06 | O1: 2026-07 | P1: 2026-08 | Q1: 2026-09 | R1: 2026-10 | S1: 2026-11 | T1: 2026-12 | U1: Expense 2026 | V1: Balance 2026-12-31
A2: Harborline Mutual Insurance | B2: General liability policy | C2: 2025-07-01 | D2: 2026-06-30 | E2: 12445 | F2: 6171.36 | G2: 0 | H2: 0 | I2: 1056.97 | J2: 954.68 | K2: 1056.97 | L2: 1022.88 | M2: 1056.97 | N2: 1022.89 | O2: 0 | P2: 0 | Q2: 0 | R2: 0 | S2: 0 | T2: 0 | U2: =SUM(I2:T2) | V2: =F2+G2-H2-U2
A3: RouteWise Software | B3: Route planning software - annual | C3: 2025-10-10 | D3: 2026-10-09 | E3: 5894 | F3: 4553.72 | G3: 0 | H3: 0 | I3: 500.59 | J3: 452.14 | K3: 500.59 | L3: 484.44 | M3: 500.59 | N3: 484.44 | O3: 500.59 | P3: 500.59 | Q3: 484.44 | R3: 145.31 | S3: 0 | T3: 0 | U3: =SUM(I3:T3) | V3: =F3+G3-H3-U3
A4: Northwest Cleaning Contractors Assn | B4: 2025 membership dues | C4: 2025-01-01 | D4: 2025-12-31 | E4: 2400 | F4: 0 | G4: 0 | H4: 0 | I4: 0 | J4: 0 | K4: 0 | L4: 0 | M4: 0 | N4: 0 | O4: 0 | P4: 0 | Q4: 0 | R4: 0 | S4: 0 | T4: 0 | U4: =SUM(I4:T4) | V4: =F4+G4-H4-U4
A5: Keystone Commercial Auto | B5: Commercial auto policy - 9 vans | C5: 2026-03-19 | D5: 2027-03-18 | E5: 25522 | F5: 0 | G5: 25522 | H5: 0 | I5: 0 | J5: 0 | K5: 909 | L5: 2097.7 | M5: 2167.62 | N5: 2097.7 | O5: 2167.62 | P5: 2167.62 | Q5: 2097.7 | R5: 2167.62 | S5: 2097.7 | T5: 2167.62 | U5: =SUM(I5:T5) | V5: =F5+G5-H5-U5
A6: Cascadia Workers' Comp Fund | B6: Workers' compensation policy | C6: 2026-04-11 | D6: 2027-04-10 | E6: 11779 | F6: 0 | G6: 11779 | H6: 0 | I6: 0 | J6: 0 | K6: 0 | L6: 645.42 | M6: 1000.41 | N6: 968.14 | O6: 1000.41 | P6: 1000.41 | Q6: 968.14 | R6: 1000.41 | S6: 968.14 | T6: 1000.41 | U6: =SUM(I6:T6) | V6: =F6+G6-H6-U6
A7: Summit Specialty Underwriters | B7: Inland marine floater - floor machines | C7: 2026-02-01 | D7: 2026-08-11 | E7: 3588 | F7: 0 | G7: 3588 | H7: 1445.54 | I7: 0 | J7: 275.24 | K7: 304.73 | L7: 294.9 | M7: 304.73 | N7: 294.9 | O7: 304.73 | P7: 363.23 | Q7: 0 | R7: 0 | S7: 0 | T7: 0 | U7: =SUM(I7:T7) | V7: =F7+G7-H7-U7
A8: Northwest Cleaning Contractors Assn | B8: 2026 membership dues | C8: 2026-01-01 | D8: 2026-12-31 | E8: 2650 | F8: 0 | G8: 2650 | H8: 0 | I8: 225.07 | J8: 203.29 | K8: 225.07 | L8: 217.81 | M8: 225.07 | N8: 217.81 | O8: 225.07 | P8: 225.07 | Q8: 217.81 | R8: 225.07 | S8: 217.81 | T8: 225.05 | U8: =SUM(I8:T8) | V8: =F8+G8-H8-U8
A9: ScrubPro Equipment Service | B9: Floor equipment service contract | C9: 2026-06-01 | D9: 2027-05-31 | E9: 5770 | F9: 0 | G9: 5770 | H9: 0 | I9: 0 | J9: 0 | K9: 0 | L9: 0 | M9: 0 | N9: 474.25 | O9: 490.05 | P9: 490.05 | Q9: 474.25 | R9: 490.05 | S9: 474.25 | T9: 490.05 | U9: =SUM(I9:T9) | V9: =F9+G9-H9-U9
A10: Total | F10: =SUM(F2:F9) | G10: =SUM(G2:G9) | H10: =SUM(H2:H9) | I10: =SUM(I2:I9) | J10: =SUM(J2:J9) | K10: =SUM(K2:K9) | L10: =SUM(L2:L9) | M10: =SUM(M2:M9) | ... V10: =SUM(V2:V9)

Sheet Roll-forward
A1: Month | B1: Opening prepaid balance | C1: Paid | D1: Refunds | E1: Amortization expense | F1: Closing prepaid balance
A2: 2026-01 | B2: =Schedule!F10 | C2: 6238 | D2: 0 | E2: =Schedule!I10 | F2: =B2+C2-D2-E2
A3: 2026-02 | B3: =F2 | C3: 0 | D3: 0 | E3: =Schedule!J10 | F3: =B3+C3-D3-E3
A4: 2026-03 | B4: =F3 | C4: 37301 | D4: 0 | E4: =Schedule!K10 | F4: =B4+C4-D4-E4
A5: 2026-04 | B5: =F4 | C5: 0 | D5: 0 | E5: =Schedule!L10 | F5: =B5+C5-D5-E5
A6: 2026-05 | B6: =F5 | C6: 5770 | D6: 0 | E6: =Schedule!M10 | F6: =B6+C6-D6-E6
A7: 2026-06 | B7: =F6 | C7: 0 | D7: 0 | E7: =Schedule!N10 | F7: =B7+C7-D7-E7
A8: 2026-07 | B8: =F7 | C8: 0 | D8: 0 | E8: =Schedule!O10 | F8: =B8+C8-D8-E8
A9: 2026-08 | B9: =F8 | C9: 0 | D9: 0 | E9: =Schedule!P10 | F9: =B9+C9-D9-E9
A10: 2026-09 | B10: =F9 | C10: 0 | D10: 1445.54 | E10: =Schedule!Q10 | F10: =B10+C10-D10-E10
A11: 2026-10 | B11: =F10 | C11: 0 | D11: 0 | E11: =Schedule!R10 | F11: =B11+C11-D11-E11
A12: 2026-11 | B12: =F11 | C12: 0 | D12: 0 | E12: =Schedule!S10 | F12: =B12+C12-D12-E12
A13: 2026-12 | B13: =F12 | C13: 0 | D13: 0 | E13: =Schedule!T10 | F13: =B13+C13-D13-E13
A14: Total 2026 | C14: =SUM(C2:C13) | D14: =SUM(D2:D13) | E14: =SUM(E2:E13) | F14: =F13
