Workbook

Sheet Variance
A1: Acct | B1: Account | C1: Type | D1: FY2026 budget | E1: Budget Jan-Jun | F1: Actual Jan-Jun | G1: Variance (+ good / - bad)
A2: 4100 | B2: Slip rentals | C2: Income | D2: 589300 | E2: =ROUND(D2*VLOOKUP(A2,Profile!$A$2:$N$18,14,FALSE),2) | F2: =ROUND(SUMIFS(GL!$C$2:$C$245,GL!$A$2:$A$245,A2),2) | G2: =IF(C2="Income",F2-E2,E2-F2)
A3: 4200 | B3: Winter storage | C3: Income | D3: 291600 | E3: =ROUND(D3*VLOOKUP(A3,Profile!$A$2:$N$18,14,FALSE),2) | F3: =ROUND(SUMIFS(GL!$C$2:$C$245,GL!$A$2:$A$245,A3),2) | G3: =IF(C3="Income",F3-E3,E3-F3)
A4: 4300 | B4: Launch and haul-out | C4: Income | D4: 179300 | E4: =ROUND(D4*VLOOKUP(A4,Profile!$A$2:$N$18,14,FALSE),2) | F4: =ROUND(SUMIFS(GL!$C$2:$C$245,GL!$A$2:$A$245,A4),2) | G4: =IF(C4="Income",F4-E4,E4-F4)
A5: 4400 | B5: Service department labor | C5: Income | D5: 244000 | E5: =ROUND(D5*VLOOKUP(A5,Profile!$A$2:$N$18,14,FALSE),2) | F5: =ROUND(SUMIFS(GL!$C$2:$C$245,GL!$A$2:$A$245,A5),2) | G5: =IF(C5="Income",F5-E5,E5-F5)
A6: 5100 | B6: Yard crew wages | C6: Expense | D6: 418700 | E6: =ROUND(D6*VLOOKUP(A6,Profile!$A$2:$N$18,14,FALSE),2) | F6: =ROUND(SUMIFS(GL!$C$2:$C$245,GL!$A$2:$A$245,A6),2) | G6: =IF(C6="Income",F6-E6,E6-F6)
A7: 5200 | B7: Seasonal dock staff | C7: Expense | D7: 154500 | E7: =ROUND(D7*VLOOKUP(A7,Profile!$A$2:$N$18,14,FALSE),2) | F7: =ROUND(SUMIFS(GL!$C$2:$C$245,GL!$A$2:$A$245,A7),2) | G7: =IF(C7="Income",F7-E7,E7-F7)
A8: 5300 | B8: Fuel | C8: Expense | D8: 58000 | E8: =ROUND(D8*VLOOKUP(A8,Profile!$A$2:$N$18,14,FALSE),2) | F8: =ROUND(SUMIFS(GL!$C$2:$C$245,GL!$A$2:$A$245,A8),2) | G8: =IF(C8="Income",F8-E8,E8-F8)
A9: 5400 | B9: Travel lift and equipment repairs | C9: Expense | D9: 37600 | E9: =ROUND(D9*VLOOKUP(A9,Profile!$A$2:$N$18,14,FALSE),2) | F9: =ROUND(SUMIFS(GL!$C$2:$C$245,GL!$A$2:$A$245,A9),2) | G9: =IF(C9="Income",F9-E9,E9-F9)
A10: 5500 | B10: Shrink-wrap and blocking supplies | C10: Expense | D10: 44700 | E10: =ROUND(D10*VLOOKUP(A10,Profile!$A$2:$N$18,14,FALSE),2) | F10: =ROUND(SUMIFS(GL!$C$2:$C$245,GL!$A$2:$A$245,A10),2) | G10: =IF(C10="Income",F10-E10,E10-F10)
A11: 6100 | B11: Office salaries | C11: Expense | D11: 130500 | E11: =ROUND(D11*VLOOKUP(A11,Profile!$A$2:$N$18,14,FALSE),2) | F11: =ROUND(SUMIFS(GL!$C$2:$C$245,GL!$A$2:$A$245,A11),2) | G11: =IF(C11="Income",F11-E11,E11-F11)
A12: 6200 | B12: Harbor lease | C12: Expense | D12: 49000 | E12: =ROUND(D12*VLOOKUP(A12,Profile!$A$2:$N$18,14,FALSE),2) | F12: =ROUND(SUMIFS(GL!$C$2:$C$245,GL!$A$2:$A$245,A12),2) | G12: =IF(C12="Income",F12-E12,E12-F12)
A13: 6300 | B13: Insurance | C13: Expense | D13: 38100 | E13: =ROUND(D13*VLOOKUP(A13,Profile!$A$2:$N$18,14,FALSE),2) | F13: =ROUND(SUMIFS(GL!$C$2:$C$245,GL!$A$2:$A$245,A13),2) | G13: =IF(C13="Income",F13-E13,E13-F13)
... A18: 6750 | B18: Crane and equipment rental | C18: Expense | D18: 0 | E18: =ROUND(D18*VLOOKUP(A18,Profile!$A$2:$N$18,14,FALSE),2) | F18: =ROUND(SUMIFS(GL!$C$2:$C$245,GL!$A$2:$A$245,A18),2) | G18: =IF(C18="Income",F18-E18,E18-F18)
B20: Total income | D20: =SUMIF($C$2:$C$18,"Income",D$2:D$18) | E20: =SUMIF($C$2:$C$18,"Income",E$2:E$18) | F20: =SUMIF($C$2:$C$18,"Income",F$2:F$18) | G20: =SUMIF($C$2:$C$18,"Income",G$2:G$18)
B21: Total expenses | D21: =SUMIF($C$2:$C$18,"Expense",D$2:D$18) | E21: =SUMIF($C$2:$C$18,"Expense",E$2:E$18) | F21: =SUMIF($C$2:$C$18,"Expense",F$2:F$18) | G21: =SUMIF($C$2:$C$18,"Expense",G$2:G$18)
B22: Net income | D22: =D20-D21 | E22: =E20-E21 | F22: =F20-F21 | G22: =G20+G21
B24: Variance is positive when it helps profit (income above budget, costs below budget) and negative when it hurts. Seasonal lines use the monthly profile from Dale's email; the rest are one twelfth a month. Crane and equipment rental has no budget line.

Sheet Profile
A1: Acct | B1: Jan | C1: Feb | D1: Mar | E1: Apr | F1: May | G1: Jun | H1: Jul | I1: Aug | J1: Sep | K1: Oct | L1: Nov | M1: Dec | N1: Share Jan-Jun
A2: 4100 | B2: 0 | C2: 0 | D2: 0 | E2: 5 | F2: 12 | G2: 18 | H2: 20 | I2: 20 | J2: 15 | K2: 10 | L2: 0 | M2: 0 | N2: =IF(SUM(B2:M2)=0,6/12,SUM(B2:G2)/SUM(B2:M2))
A3: 4200 | B3: 16 | C3: 16 | D3: 16 | E3: 8 | F3: 0 | G3: 0 | H3: 0 | I3: 0 | J3: 0 | K3: 8 | L3: 18 | M3: 18 | N3: =IF(SUM(B3:M3)=0,6/12,SUM(B3:G3)/SUM(B3:M3))
A4: 4300 | B4: 0 | C4: 0 | D4: 6 | E4: 24 | F4: 18 | G4: 4 | H4: 0 | I4: 0 | J4: 4 | K4: 20 | L4: 22 | M4: 2 | N4: =IF(SUM(B4:M4)=0,6/12,SUM(B4:G4)/SUM(B4:M4))
A5: 4400 | N5: =IF(SUM(B5:M5)=0,6/12,SUM(B5:G5)/SUM(B5:M5))
A6: 5100 | N6: =IF(SUM(B6:M6)=0,6/12,SUM(B6:G6)/SUM(B6:M6))
A7: 5200 | B7: 0 | C7: 0 | D7: 0 | E7: 8 | F7: 16 | G7: 20 | H7: 20 | I7: 20 | J7: 16 | K7: 0 | L7: 0 | M7: 0 | N7: =IF(SUM(B7:M7)=0,6/12,SUM(B7:G7)/SUM(B7:M7))
A8: 5300 | N8: =IF(SUM(B8:M8)=0,6/12,SUM(B8:G8)/SUM(B8:M8))
A9: 5400 | N9: =IF(SUM(B9:M9)=0,6/12,SUM(B9:G9)/SUM(B9:M9))
A10: 5500 | B10: 0 | C10: 0 | D10: 6 | E10: 24 | F10: 18 | G10: 4 | H10: 0 | I10: 0 | J10: 4 | K10: 20 | L10: 22 | M10: 2 | N10: =IF(SUM(B10:M10)=0,6/12,SUM(B10:G10)/SUM(B10:M10))
A11: 6100 | N11: =IF(SUM(B11:M11)=0,6/12,SUM(B11:G11)/SUM(B11:M11))
A12: 6200 | N12: =IF(SUM(B12:M12)=0,6/12,SUM(B12:G12)/SUM(B12:M12))
A13: 6300 | N13: =IF(SUM(B13:M13)=0,6/12,SUM(B13:G13)/SUM(B13:M13))
A14: 6400 | N14: =IF(SUM(B14:M14)=0,6/12,SUM(B14:G14)/SUM(B14:M14))
A15: 6500 | N15: =IF(SUM(B15:M15)=0,6/12,SUM(B15:G15)/SUM(B15:M15))
A16: 6600 | N16: =IF(SUM(B16:M16)=0,6/12,SUM(B16:G16)/SUM(B16:M16))
A17: 6700 | N17: =IF(SUM(B17:M17)=0,6/12,SUM(B17:G17)/SUM(B17:M17))
A18: 6750 | N18: =IF(SUM(B18:M18)=0,6/12,SUM(B18:G18)/SUM(B18:M18))

Sheet GL
A1: acct | B1: date | C1: amount (income and cost positive) | D1: gl account
A2: 6400 | B2: 2026-01-01 | C2: 7051.16 | D2: 640000
A3: 4400 | B3: 2026-01-02 | C3: 14013.07 | D3: 440000
A4: 5300 | B4: 2026-01-02 | C4: 1546.35 | D4: 530010
A5: 5400 | B5: 2026-01-02 | C5: 435.62 | D5: 540000
A6: 6600 | B6: 2026-01-02 | C6: 411.39 | D6: 660000
A7: 6300 | B7: 2026-01-04 | C7: 3842.16 | D7: 630000
A8: 6600 | B8: 2026-01-04 | C8: 178.29 | D8: 660000
A9: 5400 | B9: 2026-01-06 | C9: 43.83 | D9: 540000
A10: 6600 | B10: 2026-01-06 | C10: 363.81 | D10: 660000
A11: 6200 | B11: 2026-01-08 | C11: 3428.62 | D11: 620000
A12: 4200 | B12: 2026-01-09 | C12: 30891.08 | D12: 420000
A13: 5300 | B13: 2026-01-10 | C13: 3130.89 | D13: 530000
... A245: 6100 | B245: 2026-06-27 | C245: 7840.14 | D245: 610000
