Workbook

Sheet Monthly
A1: Month | B1: Depreciation expense
A2: 2026-01 | B2: =Assets!I14
A3: 2026-02 | B3: =Assets!J14
A4: 2026-03 | B4: =Assets!K14
A5: 2026-04 | B5: =Assets!L14
A6: 2026-05 | B6: =Assets!M14
A7: 2026-06 | B7: =Assets!N14
A8: 2026-07 | B8: =Assets!O14
A9: 2026-08 | B9: =Assets!P14
A10: 2026-09 | B10: =Assets!Q14
A11: 2026-10 | B11: =Assets!R14
A12: 2026-11 | B12: =Assets!S14
A13: 2026-12 | B13: =Assets!T14
A14: Total 2026 | B14: =SUM(B2:B13)

Sheet Assets
A1: Asset tag | B1: Description | C1: In service | D1: Cost | E1: Salvage | F1: Life (months) | G1: Monthly depreciation | H1: Accumulated at 2025-12-31 | I1: 2026-01 | J1: 2026-02 | K1: 2026-03 | L1: 2026-04 | M1: 2026-05 | N1: 2026-06 | O1: 2026-07 | P1: 2026-08 | Q1: 2026-09 | R1: 2026-10 | S1: 2026-11 | T1: 2026-12 | U1: 2026 depreciation | V1: Accumulated at 2026-12-31 or sale | W1: Book value (at sale if sold) | X1: Sale proceeds | Y1: Gain (loss) on sale
A2: FA-106 | B2: Rooftop HVAC unit (leasehold improvement) | C2: 44792 | D2: 22824 | E2: 0 | F2: 180 | G2: =ROUND((D2-E2)/F2,2) | H2: 5072 | I2: 126.8 | J2: 126.8 | K2: 126.8 | L2: 126.8 | M2: 126.8 | N2: 126.8 | O2: 126.8 | P2: 126.8 | Q2: 126.8 | R2: 126.8 | S2: 126.8 | T2: 126.8 | U2: =SUM(I2:T2) | V2: =H2+U2 | W2: =D2-V2
A3: FA-128 | B3: Heidelberg Speedmaster SM 52 two-color offset press | C3: 44158 | D3: 59327.2 | E3: 5650 | F3: 120 | G3: =ROUND((D3-E3)/F3,2) | H3: 27285.91 | I3: 447.31 | J3: 447.31 | K3: 447.31 | L3: 447.31 | M3: 447.31 | N3: 447.31 | O3: 447.31 | P3: 447.31 | Q3: 447.31 | R3: 447.31 | S3: 447.31 | T3: 447.31 | U3: =SUM(I3:T3) | V3: =H3+U3 | W3: =D3-V3
A4: FA-134 | B4: Mailing inserter and folder-sealer | C4: 46366 | D4: 17059.56 | E4: 0 | F4: 84 | G4: =ROUND((D4-E4)/F4,2) | H4: 0 | I4: 0 | J4: 0 | K4: 0 | L4: 0 | M4: 0 | N4: 0 | O4: 0 | P4: 0 | Q4: 0 | R4: 0 | S4: 0 | T4: 0 | U4: =SUM(I4:T4) | V4: =H4+U4 | W4: =D4-V4
A5: FA-146 | B5: 2021 Ford Transit Connect delivery van | C5: 44798 | D5: 26955.2 | E5: 5750 | F5: 60 | G5: =ROUND((D5-E5)/F5,2) | H5: 14136.8 | I5: 353.42 | J5: 353.42 | K5: 353.42 | L5: 353.42 | M5: 353.42 | N5: 353.42 | O5: 353.42 | P5: 0 | Q5: 0 | R5: 0 | S5: 0 | T5: 0 | U5: =SUM(I5:T5) | V5: =H5+U5 | W5: =D5-V5 | X5: 12850 | Y5: =X5-W5
A6: FA-150 | B6: Polar 66 guillotine paper cutter | C6: 44159 | D6: 22478.84 | E6: 1100 | F6: 84 | G6: =ROUND((D6-E6)/F6,2) | H6: 15525.11 | I6: 254.51 | J6: 254.51 | K6: 254.51 | L6: 254.51 | M6: 254.51 | N6: 254.51 | O6: 254.51 | P6: 254.51 | Q6: 254.51 | R6: 254.51 | S6: 254.51 | T6: 254.51 | U6: =SUM(I6:T6) | V6: =H6+U6 | W6: =D6-V6
A7: FA-152 | B7: MBO K70 buckle folder | C7: 44761 | D7: 15054.48 | E7: 0 | F7: 84 | G7: =ROUND((D7-E7)/F7,2) | H7: 7348.02 | I7: 179.22 | J7: 179.22 | K7: 179.22 | L7: 179.22 | M7: 179.22 | N7: 179.22 | O7: 179.22 | P7: 179.22 | Q7: 179.22 | R7: 179.22 | S7: 179.22 | T7: 179.22 | U7: =SUM(I7:T7) | V7: =H7+U7 | W7: =D7-V7
A8: FA-154 | B8: Prepress workstation and RIP server | C8: 45077 | D8: 9386.28 | E8: 0 | F8: 36 | G8: =ROUND((D8-E8)/F8,2) | H8: 8082.63 | I8: 260.73 | J8: 260.73 | K8: 260.73 | L8: 260.73 | M8: 260.73 | N8: 0 | O8: 0 | P8: 0 | Q8: 0 | R8: 0 | S8: 0 | T8: 0 | U8: =SUM(I8:T8) | V8: =H8+U8 | W8: =D8-V8
A9: FA-162 | B9: Front counter POS terminals and office PCs | C9: 45765 | D9: 4682.52 | E9: 0 | F9: 36 | G9: =ROUND((D9-E9)/F9,2) | H9: 1040.56 | I9: 130.07 | J9: 130.07 | K9: 130.07 | L9: 130.07 | M9: 130.07 | N9: 130.07 | O9: 130.07 | P9: 130.07 | Q9: 130.07 | R9: 130.07 | S9: 130.07 | T9: 130.07 | U9: =SUM(I9:T9) | V9: =H9+U9 | W9: =D9-V9
A10: FA-163 | B10: Konica Minolta AccurioPress C4080 digital press | C10: 45006 | D10: 44395 | E10: 2650 | F10: 60 | G10: =ROUND((D10-E10)/F10,2) | H10: 22959.75 | I10: 695.75 | J10: 695.75 | K10: 695.75 | L10: 695.75 | M10: 695.75 | N10: 695.75 | O10: 695.75 | P10: 695.75 | Q10: 695.75 | R10: 695.75 | S10: 695.75 | T10: 695.75 | U10: =SUM(I10:T10) | V10: =H10+U10 | W10: =D10-V10
A11: FA-166 | B11: Epson SureColor wide-format printer | C11: 45806 | D11: 13494 | E11: 0 | F11: 60 | G11: =ROUND((D11-E11)/F11,2) | H11: 1574.3 | I11: 224.9 | J11: 224.9 | K11: 224.9 | L11: 224.9 | M11: 224.9 | N11: 224.9 | O11: 224.9 | P11: 224.9 | Q11: 224.9 | R11: 224.9 | S11: 224.9 | T11: 224.9 | U11: =SUM(I11:T11) | V11: =H11+U11 | W11: =D11-V11
A12: FA-175 | B12: GBC Catena roll laminator | C12: 46091 | D12: 7828.8 | E12: 0 | F12: 60 | G12: =ROUND((D12-E12)/F12,2) | H12: 0 | I12: 0 | J12: 0 | K12: 0 | L12: 130.48 | M12: 130.48 | N12: 130.48 | O12: 130.48 | P12: 130.48 | Q12: 130.48 | R12: 130.48 | S12: 130.48 | T12: 130.48 | U12: =SUM(I12:T12) | V12: =H12+U12 | W12: =D12-V12
A13: FA-198 | B13: 2026 Ford Transit 250 cargo van | C13: 46174 | D13: 50261.4 | E13: 9600 | F13: 60 | G13: =ROUND((D13-E13)/F13,2) | H13: 0 | I13: 0 | J13: 0 | K13: 0 | L13: 0 | M13: 0 | N13: 0 | O13: 677.69 | P13: 677.69 | Q13: 677.69 | R13: 677.69 | S13: 677.69 | T13: 677.69 | U13: =SUM(I13:T13) | V13: =H13+U13 | W13: =D13-V13
A14: Total | D14: =SUM(D2:D13) | E14: =SUM(E2:E13) | H14: =SUM(H2:H13) | I14: =SUM(I2:I13) | J14: =SUM(J2:J13) | K14: =SUM(K2:K13) | L14: =SUM(L2:L13) | M14: =SUM(M2:M13) | N14: =SUM(N2:N13) | O14: =SUM(O2:O13) | ... W14: =SUM(W2:W13)
