Workbook

Sheet Burn
A1: Cost code | B1: Description | C1: Budget | D1: Spent | E1: Committed | F1: Remaining
A2: WG-01 | B2: General conditions | C2: 119000 | D2: =SUMIFS(Invoices!$F$2:$F$31,Invoices!$E$2:$E$31,A2,Invoices!$G$2:$G$31,"Posted") | E2: =SUMIFS(POs!$I$2:$I$10,POs!$C$2:$C$10,A2) | F2: =C2-D2-E2
A3: WG-02 | B3: Demolition and abatement | C3: 49000 | D3: =SUMIFS(Invoices!$F$2:$F$31,Invoices!$E$2:$E$31,A3,Invoices!$G$2:$G$31,"Posted") | E3: =SUMIFS(POs!$I$2:$I$10,POs!$C$2:$C$10,A3) | F3: =C3-D3-E3
A4: WG-03 | B4: Electrical | C4: 125000 | D4: =SUMIFS(Invoices!$F$2:$F$31,Invoices!$E$2:$E$31,A4,Invoices!$G$2:$G$31,"Posted") | E4: =SUMIFS(POs!$I$2:$I$10,POs!$C$2:$C$10,A4) | F4: =C4-D4-E4
A5: WG-04 | B5: HVAC | C5: 115000 | D5: =SUMIFS(Invoices!$F$2:$F$31,Invoices!$E$2:$E$31,A5,Invoices!$G$2:$G$31,"Posted") | E5: =SUMIFS(POs!$I$2:$I$10,POs!$C$2:$C$10,A5) | F5: =C5-D5-E5
A6: WG-05 | B6: Exhibit fabrication | C6: 296000 | D6: =SUMIFS(Invoices!$F$2:$F$31,Invoices!$E$2:$E$31,A6,Invoices!$G$2:$G$31,"Posted") | E6: =SUMIFS(POs!$I$2:$I$10,POs!$C$2:$C$10,A6) | F6: =C6-D6-E6
A7: WG-06 | B7: Gallery lighting | C7: 65000 | D7: =SUMIFS(Invoices!$F$2:$F$31,Invoices!$E$2:$E$31,A7,Invoices!$G$2:$G$31,"Posted") | E7: =SUMIFS(POs!$I$2:$I$10,POs!$C$2:$C$10,A7) | F7: =C7-D7-E7
A8: WG-07 | B8: AV and interactive media | C8: 87000 | D8: =SUMIFS(Invoices!$F$2:$F$31,Invoices!$E$2:$E$31,A8,Invoices!$G$2:$G$31,"Posted") | E8: =SUMIFS(POs!$I$2:$I$10,POs!$C$2:$C$10,A8) | F8: =C8-D8-E8
A9: WG-08 | B9: Design and engineering fees | C9: 98000 | D9: =SUMIFS(Invoices!$F$2:$F$31,Invoices!$E$2:$E$31,A9,Invoices!$G$2:$G$31,"Posted") | E9: =SUMIFS(POs!$I$2:$I$10,POs!$C$2:$C$10,A9) | F9: =C9-D9-E9
A10: WG-09 | B10: Permits and inspections | C10: 7500 | D10: =SUMIFS(Invoices!$F$2:$F$31,Invoices!$E$2:$E$31,A10,Invoices!$G$2:$G$31,"Posted") | E10: =SUMIFS(POs!$I$2:$I$10,POs!$C$2:$C$10,A10) | F10: =C10-D10-E10
A11: WG-10 | B11: Owner contingency | C11: 65000 | D11: =SUMIFS(Invoices!$F$2:$F$31,Invoices!$E$2:$E$31,A11,Invoices!$G$2:$G$31,"Posted") | E11: =SUMIFS(POs!$I$2:$I$10,POs!$C$2:$C$10,A11) | F11: =C11-D11-E11
B12: Total | C12: =SUM(C2:C11) | D12: =SUM(D2:D11) | E12: =SUM(E2:E11) | F12: =SUM(F2:F11)

Sheet POs
A1: PO | B1: Vendor | C1: Cost code | D1: Description | E1: Status | F1: Original amount | G1: Approved change orders | H1: Invoiced | I1: Still committed
A2: PO-2026-015 | B2: Harbor & Finch Builders | C2: WG-01 | D2: General contractor fee and site supervision | E2: Open | F2: 110500 | G2: =SUMIFS('Change orders'!$E$2:$E$6,'Change orders'!$B$2:$B$6,A2,'Change orders'!$F$2:$F$6,"Approved") | H2: =SUMIFS(Invoices!$F$2:$F$31,Invoices!$D$2:$D$31,A2,Invoices!$G$2:$G$31,"Posted") | I2: =IF(E2="Open",MAX(0,F2+G2-H2),0)
A3: PO-2026-017 | B3: Coastline Demolition & Abatement | C3: WG-02 | D3: Selective demolition, lead paint abatement | E3: Closed | F3: 42500 | G3: =SUMIFS('Change orders'!$E$2:$E$6,'Change orders'!$B$2:$B$6,A3,'Change orders'!$F$2:$F$6,"Approved") | H3: =SUMIFS(Invoices!$F$2:$F$31,Invoices!$D$2:$D$31,A3,Invoices!$G$2:$G$31,"Posted") | I3: =IF(E3="Open",MAX(0,F3+G3-H3),0)
A4: PO-2026-018 | B4: Brightwire Electrical Contractors | C4: WG-03 | D4: Branch circuits, panel upgrade, exhibit power | E4: Closed | F4: 102000 | G4: =SUMIFS('Change orders'!$E$2:$E$6,'Change orders'!$B$2:$B$6,A4,'Change orders'!$F$2:$F$6,"Approved") | H4: =SUMIFS(Invoices!$F$2:$F$31,Invoices!$D$2:$D$31,A4,Invoices!$G$2:$G$31,"Posted") | I4: =IF(E4="Open",MAX(0,F4+G4-H4),0)
A5: PO-2026-021 | B5: Brightwire Electrical Contractors | C5: WG-03 | D5: Exhibit case outlets (added scope) | E5: Open | F5: 7600 | G5: =SUMIFS('Change orders'!$E$2:$E$6,'Change orders'!$B$2:$B$6,A5,'Change orders'!$F$2:$F$6,"Approved") | H5: =SUMIFS(Invoices!$F$2:$F$31,Invoices!$D$2:$D$31,A5,Invoices!$G$2:$G$31,"Posted") | I5: =IF(E5="Open",MAX(0,F5+G5-H5),0)
A6: PO-2026-024 | B6: Seaboard Mechanical | C6: WG-04 | D6: Gallery HVAC with humidity control | E6: Open | F6: 87000 | G6: =SUMIFS('Change orders'!$E$2:$E$6,'Change orders'!$B$2:$B$6,A6,'Change orders'!$F$2:$F$6,"Approved") | H6: =SUMIFS(Invoices!$F$2:$F$31,Invoices!$D$2:$D$31,A6,Invoices!$G$2:$G$31,"Posted") | I6: =IF(E6="Open",MAX(0,F6+G6-H6),0)
A7: PO-2026-025 | B7: Keelhaul Exhibit Studio | C7: WG-05 | D7: Exhibit fabrication and installation | E7: Open | F7: 213000 | G7: =SUMIFS('Change orders'!$E$2:$E$6,'Change orders'!$B$2:$B$6,A7,'Change orders'!$F$2:$F$6,"Approved") | H7: =SUMIFS(Invoices!$F$2:$F$31,Invoices!$D$2:$D$31,A7,Invoices!$G$2:$G$31,"Posted") | I7: =IF(E7="Open",MAX(0,F7+G7-H7),0)
A8: PO-2026-028 | B8: Lumenharbor Lighting | C8: WG-06 | D8: Track lighting and fixtures | E8: Open | F8: 59250 | G8: =SUMIFS('Change orders'!$E$2:$E$6,'Change orders'!$B$2:$B$6,A8,'Change orders'!$F$2:$F$6,"Approved") | H8: =SUMIFS(Invoices!$F$2:$F$31,Invoices!$D$2:$D$31,A8,Invoices!$G$2:$G$31,"Posted") | I8: =IF(E8="Open",MAX(0,F8+G8-H8),0)
A9: PO-2026-030 | B9: Signal & Tide Media | C9: WG-07 | D9: Projection and touchscreen interactives | E9: Open | F9: 74000 | G9: =SUMIFS('Change orders'!$E$2:$E$6,'Change orders'!$B$2:$B$6,A9,'Change orders'!$F$2:$F$6,"Approved") | H9: =SUMIFS(Invoices!$F$2:$F$31,Invoices!$D$2:$D$31,A9,Invoices!$G$2:$G$31,"Posted") | I9: =IF(E9="Open",MAX(0,F9+G9-H9),0)
A10: PO-2026-031 | B10: Northbeam AV Integration | C10: WG-07 | D10: Projection package (vendor replaced) | E10: Cancelled | F10: 57500 | G10: =SUMIFS('Change orders'!$E$2:$E$6,'Change orders'!$B$2:$B$6,A10,'Change orders'!$F$2:$F$6,"Approved") | H10: =SUMIFS(Invoices!$F$2:$F$31,Invoices!$D$2:$D$31,A10,Invoices!$G$2:$G$31,"Posted") | I10: =IF(E10="Open",MAX(0,F10+G10-H10),0)

Sheet Invoices
A1: Invoice | B1: Vendor | C1: Date | D1: PO | E1: Cost code | F1: Amount | G1: Status
A2: HF-9376 | B2: Harbor & Finch Builders | C2: 2026-02-27 | D2: PO-2026-015 | E2: WG-01 | F2: 11050 | G2: Posted
A3: HF-7634 | B3: Harbor & Finch Builders | C3: 2026-03-28 | D3: PO-2026-015 | E3: WG-01 | F3: 11050 | G3: Posted
A4: HF-8808 | B4: Harbor & Finch Builders | C4: 2026-04-27 | D4: PO-2026-015 | E4: WG-01 | F4: 11050 | G4: Posted
A5: HF-4578 | B5: Harbor & Finch Builders | C5: 2026-05-27 | D5: PO-2026-015 | E5: WG-01 | F5: 11050 | G5: Posted
A6: HF-5617 | B6: Harbor & Finch Builders | C6: 2026-06-26 | D6: PO-2026-015 | E6: WG-01 | F6: 11050 | G6: Posted
A7: HF-2553 | B7: Harbor & Finch Builders | C7: 2026-07-26 | D7: PO-2026-015 | E7: WG-01 | F7: 11050 | G7: Posted
A8: HF-9725 | B8: Harbor & Finch Builders | C8: 2026-08-27 | D8: PO-2026-015 | E8: WG-01 | F8: 11050 | G8: Posted
A9: CDA-2208 | B9: Coastline Demolition & Abatement | C9: 2026-02-11 | D9: PO-2026-017 | E9: WG-02 | F9: 25500 | G9: Posted
A10: CDA-6409 | B10: Coastline Demolition & Abatement | C10: 2026-03-15 | D10: PO-2026-017 | E10: WG-02 | F10: 17000 | G10: Posted
A11: BW6180 | B11: Brightwire Electrical Contractors | C11: 2026-03-16 | D11: PO-2026-018 | E11: WG-03 | F11: 35700 | G11: Posted
A12: BW8815 | B12: Brightwire Electrical Contractors | C12: 2026-05-09 | D12: PO-2026-018 | E12: WG-03 | F12: 40800 | G12: Posted
A13: BW9541 | B13: Brightwire Electrical Contractors | C13: 2026-07-17 | D13: PO-2026-018 | E13: WG-03 | F13: 19380 | G13: Posted
... A24: STM-8807 | B24: Signal & Tide Media | C24: 2026-08-18 | D24: PO-2026-030 | E24: WG-07 | F24: 4172.87 | G24: Posted
A25: MPA-3133 | B25: Marlow Pike Architects | C25: 2026-02-11 | E25: WG-08 | F25: 7648.82 | G25: Posted
A26: MPA-2314 | B26: Marlow Pike Architects | C26: 2026-01-29 | E26: WG-08 | F26: 9336.29 | G26: Posted
A27: MPA-7410 | B27: Marlow Pike Architects | C27: 2026-07-13 | E27: WG-08 | F27: 17537.2 | G27: Posted
A28: MPA-9549 | B28: Marlow Pike Architects | C28: 2026-03-31 | E28: WG-08 | F28: 17201.11 | G28: Posted
A29: HSE-7871 | B29: Holloway Structural Engineers | C29: 2026-03-08 | E29: WG-08 | F29: 5034.7 | G29: Posted
A30: BLD-9071 | B30: City of Tidewater Permits | C30: 2026-02-16 | E30: WG-09 | F30: 3542.89 | G30: Posted
A31: INSP-6855 | B31: City of Tidewater Permits | C31: 2026-07-22 | E31: WG-09 | F31: 782.69 | G31: Posted

Sheet Change orders
A1: CO | B1: PO | C1: Date | D1: Description | E1: Amount | F1: Status
A2: CO-01 | B2: PO-2026-024 | C2: 2026-06-03 | D2: Added dehumidifier for ship-model cases | E2: 12250 | F2: Pending
A3: CO-02 | B3: PO-2026-025 | C3: 2026-05-06 | D3: Interactive tide table build-out | E3: 26250 | F3: Approved
A4: CO-03 | B4: PO-2026-025 | C4: 2026-06-06 | D4: Delete second graphics rail | E4: -3500 | F4: Approved
A5: CO-04 | B5: PO-2026-025 | C5: 2026-07-21 | D5: Replica figurehead upgrade | E5: 12000 | F5: Pending
A6: CO-05 | B6: PO-2026-025 | C6: 2026-06-20 | D6: Walnut veneer in lieu of paint | E6: 4750 | F6: Rejected
